Ejemplos_Clase/Codificadores_mux_demux/demux.v
module sensor_demux(

    input  wire [1:0] sel,

    output reg enable0,
    output reg enable1,
    output reg enable2,
    output reg enable3

);

always @(*) begin

    enable0 = 1'b0;
    enable1 = 1'b0;
    enable2 = 1'b0;
    enable3 = 1'b0;

    case(sel)

        2'b00: enable0 = 1'b1;
        2'b01: enable1 = 1'b1;
        2'b10: enable2 = 1'b1;
        2'b11: enable3 = 1'b1;

    endcase

end

endmodule

Ejemplos_Clase/Codificadores_mux_demux/bin_to_bcd.v
module bin_to_bcd(

    input  wire [3:0] bin,
    output reg  [7:0] bcd

);

always @(*) begin

    case(bin)

        4'd0:  bcd = 8'b0000_0000;
        4'd1:  bcd = 8'b0000_0001;
        4'd2:  bcd = 8'b0000_0010;
        4'd3:  bcd = 8'b0000_0011;
        4'd4:  bcd = 8'b0000_0100;
        4'd5:  bcd = 8'b0000_0101;
        4'd6:  bcd = 8'b0000_0110;
        4'd7:  bcd = 8'b0000_0111;
        4'd8:  bcd = 8'b0000_1000;
        4'd9:  bcd = 8'b0000_1001;

        4'd10: bcd = 8'b0001_0000;
        4'd11: bcd = 8'b0001_0001;
        4'd12: bcd = 8'b0001_0010;
        4'd13: bcd = 8'b0001_0011;
        4'd14: bcd = 8'b0001_0100;
        4'd15: bcd = 8'b0001_0101;

        default: bcd = 8'b0000_0000;

    endcase

end

endmodule

Ejemplos_Clase/Codificadores_mux_demux/Mux.v
module sensor_mux(

    input  wire [3:0] sensor0,
    input  wire [3:0] sensor1,
    input  wire [3:0] sensor2,
    input  wire [3:0] sensor3,

    input  wire [1:0] sel,

    output reg  [3:0] data_out

);
always @(*) begin

    case(sel)

        2'b00: data_out = sensor0;
        2'b01: data_out = sensor1;
        2'b10: data_out = sensor2;
        2'b11: data_out = sensor3;

        default: data_out = 4'b0000;

    endcase

end

endmodule

Ejemplos_Clase/Codificadores_mux_demux/top.v
module sensor_system_top(

    input  wire [3:0] sensor0,
    input  wire [3:0] sensor1,
    input  wire [3:0] sensor2,
    input  wire [3:0] sensor3,

    input  wire [1:0] sel,

    output wire [7:0] bcd_data,

    output wire enable0,
    output wire enable1,
    output wire enable2,
    output wire enable3

);

wire [3:0] mux_out;

sensor_mux mux_inst(

    .sensor0(sensor0),
    .sensor1(sensor1),
    .sensor2(sensor2),
    .sensor3(sensor3),

    .sel(sel),

    .data_out(mux_out)

);

bin_to_bcd bcd_inst(

    .bin(mux_out),
    .bcd(bcd_data)

);

sensor_demux demux_inst(

    .sel(sel),

    .enable0(enable0),
    .enable1(enable1),
    .enable2(enable2),
    .enable3(enable3)

);

endmodule

Ejemplos_Clase/Codificadores_mux_demux/system_tb.v
`timescale 1ns/1ps

module sensor_system_tb;

reg [3:0] sensor0;
reg [3:0] sensor1;
reg [3:0] sensor2;
reg [3:0] sensor3;

reg [1:0] sel;

wire [7:0] bcd_data;

wire enable0;
wire enable1;
wire enable2;
wire enable3;

sensor_system_top uut(

    .sensor0(sensor0),
    .sensor1(sensor1),
    .sensor2(sensor2),
    .sensor3(sensor3),

    .sel(sel),

    .bcd_data(bcd_data),

    .enable0(enable0),
    .enable1(enable1),
    .enable2(enable2),
    .enable3(enable3)

);

initial begin

    // Archivo de ondas para GTKWave
    $dumpfile("sensor_system.vcd");
    $dumpvars(0, sensor_system_tb);

end

initial begin

    $display("Inicio de simulacion");

    sensor0 = 4'd3;
    sensor1 = 4'd7;
    sensor2 = 4'd12;
    sensor3 = 4'd9;

    sel = 2'b00; #10;
    sel = 2'b01; #10;
    sel = 2'b10; #10;
    sel = 2'b11; #10;

    sensor0 = 4'd5;
    sensor1 = 4'd10;
    sensor2 = 4'd2;
    sensor3 = 4'd15;

    sel = 2'b00; #10;
    sel = 2'b01; #10;
    sel = 2'b10; #10;
    sel = 2'b11; #10;

    sensor0 = 4'd0;
    sensor1 = 4'd1;
    sensor2 = 4'd8;
    sensor3 = 4'd4;

    sel = 2'b10; #10;
    sel = 2'b01; #10;

    $display("Fin de simulacion");
    $finish;

end

endmodule

Ejemplos_Clase/Codificadores_mux_demux/sensor_system.vcd
$date
	Tue Mar 24 07:54:27 2026
$end
$version
	Icarus Verilog
$end
$timescale
	1ps
$end
$scope module sensor_system_tb $end
$var wire 1 ! enable3 $end
$var wire 1 " enable2 $end
$var wire 1 # enable1 $end
$var wire 1 $ enable0 $end
$var wire 8 % bcd_data [7:0] $end
$var reg 2 & sel [1:0] $end
$var reg 4 ' sensor0 [3:0] $end
$var reg 4 ( sensor1 [3:0] $end
$var reg 4 ) sensor2 [3:0] $end
$var reg 4 * sensor3 [3:0] $end
$scope module uut $end
$var wire 2 + sel [1:0] $end
$var wire 4 , sensor0 [3:0] $end
$var wire 4 - sensor1 [3:0] $end
$var wire 4 . sensor2 [3:0] $end
$var wire 4 / sensor3 [3:0] $end
$var wire 4 0 mux_out [3:0] $end
$var wire 1 ! enable3 $end
$var wire 1 " enable2 $end
$var wire 1 # enable1 $end
$var wire 1 $ enable0 $end
$var wire 8 1 bcd_data [7:0] $end
$scope module bcd_inst $end
$var wire 4 2 bin [3:0] $end
$var reg 8 3 bcd [7:0] $end
$upscope $end
$scope module demux_inst $end
$var wire 2 4 sel [1:0] $end
$var reg 1 $ enable0 $end
$var reg 1 # enable1 $end
$var reg 1 " enable2 $end
$var reg 1 ! enable3 $end
$upscope $end
$scope module mux_inst $end
$var wire 2 5 sel [1:0] $end
$var wire 4 6 sensor0 [3:0] $end
$var wire 4 7 sensor1 [3:0] $end
$var wire 4 8 sensor2 [3:0] $end
$var wire 4 9 sensor3 [3:0] $end
$var reg 4 : data_out [3:0] $end
$upscope $end
$upscope $end
$upscope $end
$enddefinitions $end
#0
$dumpvars
b11 :
b1001 9
b1100 8
b111 7
b11 6
b0 5
b0 4
b11 3
b11 2
b11 1
b11 0
b1001 /
b1100 .
b111 -
b11 ,
b0 +
b1001 *
b1100 )
b111 (
b11 '
b0 &
b11 %
1$
0#
0"
0!
$end
#10000
b111 %
b111 1
b111 3
1#
0$
b111 0
b111 2
b111 :
b1 &
b1 +
b1 4
b1 5
#20000
b10010 %
b10010 1
b10010 3
1"
0#
b1100 0
b1100 2
b1100 :
b10 &
b10 +
b10 4
b10 5
#30000
b1001 %
b1001 1
b1001 3
1!
0"
b1001 0
b1001 2
b1001 :
b11 &
b11 +
b11 4
b11 5
#40000
b101 %
b101 1
b101 3
1$
0!
b101 0
b101 2
b101 :
b0 &
b0 +
b0 4
b0 5
b1111 *
b1111 /
b1111 9
b10 )
b10 .
b10 8
b1010 (
b1010 -
b1010 7
b101 '
b101 ,
b101 6
#50000
b10000 %
b10000 1
b10000 3
1#
0$
b1010 0
b1010 2
b1010 :
b1 &
b1 +
b1 4
b1 5
#60000
b10 %
b10 1
b10 3
1"
0#
b10 0
b10 2
b10 :
b10 &
b10 +
b10 4
b10 5
#70000
b10101 %
b10101 1
b10101 3
1!
0"
b1111 0
b1111 2
b1111 :
b11 &
b11 +
b11 4
b11 5
#80000
b1000 %
b1000 1
b1000 3
1"
0!
b1000 0
b1000 2
b1000 :
b10 &
b10 +
b10 4
b10 5
b100 *
b100 /
b100 9
b1000 )
b1000 .
b1000 8
b1 (
b1 -
b1 7
b0 '
b0 ,
b0 6
#90000
b1 %
b1 1
b1 3
1#
0"
b1 0
b1 2
b1 :
b1 &
b1 +
b1 4
b1 5
