Ejemplos_Clase/FSM/servo.v
module servo_controller(
    input clk,
    input rst,
    input abrir,
    input cerrar,
    output reg servo_pwm
);

parameter CLK_FREQ = 50_000_000;
parameter PWM_PERIOD = 1_000_000;

parameter OPEN_PULSE  = 100_000;
parameter CLOSE_PULSE = 50_000;

reg [31:0] counter;
reg [31:0] pulse_width;

always @(posedge clk) begin

    if(rst)
        pulse_width <= CLOSE_PULSE;

    else begin

        if(abrir)
            pulse_width <= OPEN_PULSE;

        else if(cerrar)
            pulse_width <= CLOSE_PULSE;

    end

end

always @(posedge clk) begin

    if(rst)
        counter <= 0;

    else if(counter >= PWM_PERIOD-1)
        counter <= 0;

    else
        counter <= counter + 1;

end

always @(*) begin

    if(counter < pulse_width)
        servo_pwm = 1;

    else
        servo_pwm = 0;

end

endmodule

Ejemplos_Clase/FSM/fsm_parqueadero.v
module fsm_parqueadero(

    input clk,
    input rst,

    input sensor_vehiculo,
    input dato_listo,
    input id_correcto,
    input sensor_salida,
    input timer_done,

    output reg shift_enable,
    output reg comparar_enable,
    output reg servo_abrir,
    output reg servo_cerrar,
    output reg timer_enable

);

//////////////////////////////////////////////////
// Estados
//////////////////////////////////////////////////

localparam IDLE     = 3'b000;
localparam LEER     = 3'b001;
localparam VALIDAR  = 3'b010;
localparam ABRIR    = 3'b011;
localparam ESPERAR  = 3'b100;
localparam CERRAR   = 3'b101;

//////////////////////////////////////////////////
// Registros de estado
//////////////////////////////////////////////////

reg [2:0] estado_actual;
reg [2:0] siguiente_estado;

//////////////////////////////////////////////////
// Registro de estado
//////////////////////////////////////////////////

always @(posedge clk) begin

    if(rst)
        estado_actual <= IDLE;
    else
        estado_actual <= siguiente_estado;

end

//////////////////////////////////////////////////
// Lógica de transición
//////////////////////////////////////////////////

always @(*) begin

    // Valor por defecto
    siguiente_estado = estado_actual;

    case(estado_actual)

        //////////////////////////////////////////
        // Estado IDLE
        //////////////////////////////////////////

        IDLE: begin

            if(sensor_vehiculo)
                siguiente_estado = LEER;
            else
                siguiente_estado = IDLE;

        end

        //////////////////////////////////////////
        // Estado LEER
        //////////////////////////////////////////

        LEER: begin

            if(dato_listo)
                siguiente_estado = VALIDAR;
            else
                siguiente_estado = LEER;

        end

        //////////////////////////////////////////
        // Estado VALIDAR
        //////////////////////////////////////////

        VALIDAR: begin

            if(id_correcto)
                siguiente_estado = ABRIR;
            else
                siguiente_estado = IDLE;

        end

        //////////////////////////////////////////
        // Estado ABRIR
        //////////////////////////////////////////

        ABRIR: begin

            if(timer_done)
                siguiente_estado = ESPERAR;
            else
                siguiente_estado = ABRIR;

        end

        //////////////////////////////////////////
        // Estado ESPERAR
        //////////////////////////////////////////

        ESPERAR: begin

            if(sensor_salida)
                siguiente_estado = CERRAR;
            else
                siguiente_estado = ESPERAR;

        end

        //////////////////////////////////////////
        // Estado CERRAR
        //////////////////////////////////////////

        CERRAR: begin

            if(timer_done)
                siguiente_estado = IDLE;
            else
                siguiente_estado = CERRAR;

        end

        //////////////////////////////////////////
        // Estado por defecto
        //////////////////////////////////////////

        default: begin

            siguiente_estado = IDLE;

        end

    endcase

end

//////////////////////////////////////////////////
// Lógica de salida
//////////////////////////////////////////////////

always @(*) begin

    // Valores por defecto
    shift_enable     = 0;
    comparar_enable  = 0;
    servo_abrir      = 0;
    servo_cerrar     = 0;
    timer_enable     = 0;

    case(estado_actual)

        //////////////////////////////////////////
        // LEER
        //////////////////////////////////////////

        LEER: begin

            shift_enable = 1;

        end

        //////////////////////////////////////////
        // VALIDAR
        //////////////////////////////////////////

        VALIDAR: begin

            comparar_enable = 1;

        end

        //////////////////////////////////////////
        // ABRIR
        //////////////////////////////////////////

        ABRIR: begin

            servo_abrir  = 1;
            timer_enable = 1;

        end

        //////////////////////////////////////////
        // CERRAR
        //////////////////////////////////////////

        CERRAR: begin

            servo_cerrar = 1;
            timer_enable = 1;

        end

    endcase

end

endmodule

Ejemplos_Clase/FSM/timer.v
module timer #(
    parameter MAX_COUNT = 50_000_000
)(
    input clk,
    input rst,
    input enable,
    output reg done
);

reg [31:0] counter;

always @(posedge clk) begin

    if(rst) begin
        counter <= 0;
        done <= 0;
    end

    else if(enable) begin

        if(counter == MAX_COUNT-1) begin
            counter <= 0;
            done <= 1;
        end

        else begin
            counter <= counter + 1;
            done <= 0;
        end

    end

    else begin
        counter <= 0;
        done <= 0;
    end

end

endmodule

Ejemplos_Clase/FSM/comparador_id.v
module comparador_id #(
    parameter N = 8,
    parameter PASSWORD = 8'b10110011
)(
    input [N-1:0] data,
    output id_correcto
);

assign id_correcto = (data == PASSWORD);

endmodule

Ejemplos_Clase/FSM/shift_register.v
module shift_register #(
    parameter N = 8
)(
    input clk,
    input rst,
    input enable,
    input serial_in,
    output reg [N-1:0] data
);

always @(posedge clk) begin
    if(rst)
        data <= 0;

    else if(enable)
        data <= {data[N-2:0], serial_in};

end

endmodule

Ejemplos_Clase/FSM/top.v
module top_parqueadero(
    input clk,
    input rst,

    input sensor_vehiculo,
    input bit_serial,
    input dato_listo,
    input sensor_salida,

    output servo_pwm
);

//-------------------------------------------------
// Señales internas
//-------------------------------------------------

wire shift_enable;
wire comparar_enable;
wire servo_abrir;
wire servo_cerrar;
wire timer_enable;

wire [7:0] password_data;

wire id_correcto;
wire timer_done;

//-------------------------------------------------
// Shift Register
//-------------------------------------------------

shift_register shift0(
    .clk(clk),
    .rst(rst),
    .enable(shift_enable),
    .serial_in(bit_serial),
    .data(password_data)
);

//-------------------------------------------------
// Comparador
//-------------------------------------------------

comparador_id comp0(
    .data(password_data),
    .id_correcto(id_correcto)
);

//-------------------------------------------------
// Timer
//-------------------------------------------------

timer timer0(
    .clk(clk),
    .rst(rst),
    .enable(timer_enable),
    .done(timer_done)
);

//-------------------------------------------------
// FSM
//-------------------------------------------------

fsm_parqueadero fsm0(
    .clk(clk),
    .rst(rst),

    .sensor_vehiculo(sensor_vehiculo),
    .dato_listo(dato_listo),
    .id_correcto(id_correcto),
    .sensor_salida(sensor_salida),

    .timer_done(timer_done),

    .shift_enable(shift_enable),
    .comparar_enable(comparar_enable),

    .servo_abrir(servo_abrir),
    .servo_cerrar(servo_cerrar),

    .timer_enable(timer_enable)
);

//-------------------------------------------------
// Servo Controller
//-------------------------------------------------

servo_controller servo0(
    .clk(clk),
    .rst(rst),

    .abrir(servo_abrir),
    .cerrar(servo_cerrar),

    .servo_pwm(servo_pwm)
);

endmodule

Ejemplos_Clase/FSM/tb_top.v
`timescale 1ns/1ps

module tb_top_parqueadero;

//-------------------------------------------------
// Entradas
//-------------------------------------------------

reg clk;
reg rst;

reg sensor_vehiculo;
reg bit_serial;
reg dato_listo;
reg sensor_salida;

//-------------------------------------------------
// Salidas
//-------------------------------------------------

wire servo_pwm;

//-------------------------------------------------
// DUT
//-------------------------------------------------

top_parqueadero dut(
    .clk(clk),
    .rst(rst),
    .sensor_vehiculo(sensor_vehiculo),
    .bit_serial(bit_serial),
    .dato_listo(dato_listo),
    .sensor_salida(sensor_salida),
    .servo_pwm(servo_pwm)
);

//-------------------------------------------------
// Reducir timer para simulación rápida
//-------------------------------------------------

defparam dut.timer0.MAX_COUNT = 20;

//-------------------------------------------------
// Clock
//-------------------------------------------------

always #10 clk = ~clk;

//-------------------------------------------------
// Task: enviar password serial
//-------------------------------------------------

task send_password;

    input [7:0] password;

    integer i;

    begin

        $display("Enviando password...");

        for(i=7; i>0; i=i-1) begin

            bit_serial = password[i];

            $display("Bit enviado = %b", password[i]);

            #20;

        end

    end

endtask

//-------------------------------------------------
// Monitor
//-------------------------------------------------

always @(posedge clk) begin

    $display(
        "T=%0t | Estado=%b | Shift=%b | ID_OK=%b | Abrir=%b | Cerrar=%b",
        $time,
        dut.fsm0.estado_actual,
        dut.shift_enable,
        dut.id_correcto,
        dut.servo_abrir,
        dut.servo_cerrar
    );

end

//-------------------------------------------------
// Inicialización
//-------------------------------------------------

initial begin

    $dumpfile("waveform.vcd");
    $dumpvars(0, tb_top_parqueadero);

    clk = 0;
    rst = 1;

    sensor_vehiculo = 0;
    bit_serial = 0;
    dato_listo = 0;
    sensor_salida = 0;

    //-------------------------------------------------
    // RESET
    //-------------------------------------------------

    #100;
    rst = 0;

    $display("\n===== RESET LIBERADO =====");

    //-------------------------------------------------
    // CASO 1:
    // Password correcta
    //-------------------------------------------------

    $display("\n===== CASO 1: PASSWORD CORRECTA =====");

    // Vehículo llega

    #100;
    sensor_vehiculo = 1;

    #200;
    sensor_vehiculo = 0;

    // Esperar FSM -> LEER

    #100;

    // Enviar password correcta

    send_password(8'b10110011);

    // Datos listos

    dato_listo = 1;

    #40;
    dato_listo = 0;

    // Esperar apertura

    #1000;

    // Vehículo pasa

    sensor_salida = 1;

    #200;
    sensor_salida = 0;

    // Esperar cierre

    #1000;

    //-------------------------------------------------
    // CASO 2:
    // Password incorrecta
    //-------------------------------------------------

    $display("\n===== CASO 2: PASSWORD INCORRECTA =====");

    #500;

    sensor_vehiculo = 1;

    #40;
    sensor_vehiculo = 0;

    #100;

    // Password incorrecta

    send_password(8'b11111111);

    dato_listo = 1;

    #40;
    dato_listo = 0;

    // Debe regresar a IDLE

    #500;

    //-------------------------------------------------
    // CASO 3:
    // dato_listo nunca llega
    //-------------------------------------------------

    $display("\n===== CASO 3: ESPERA EN LEER =====");

    sensor_vehiculo = 1;

    #40;
    sensor_vehiculo = 0;

    // FSM debe quedarse en LEER

    #1000;

    //-------------------------------------------------
    // CASO 4:
    // sensor_salida tarda en activarse
    //-------------------------------------------------

    $display("\n===== CASO 4: ESPERA EN ESPERAR =====");

    rst = 1;
    #40;
    rst = 0;

    #100;

    sensor_vehiculo = 1;

    #40;
    sensor_vehiculo = 0;

    #100;

    send_password(8'b10110011);

    dato_listo = 1;

    #40;
    dato_listo = 0;

    // Esperar mucho tiempo sin salida

    #2000;

    sensor_salida = 1;

    #40;
    sensor_salida = 0;

    #1000;

    //-------------------------------------------------
    // FIN
    //-------------------------------------------------

    $display("\n===== FIN SIMULACION =====");

    $finish;

end

endmodule

Ejemplos_Clase/FSM/waveform.vcd
$date
	Mon May 18 18:18:23 2026
$end
$version
	Icarus Verilog
$end
$timescale
	1ps
$end
$scope module tb_top_parqueadero $end
$var wire 1 ! servo_pwm $end
$var reg 1 " bit_serial $end
$var reg 1 # clk $end
$var reg 1 $ dato_listo $end
$var reg 1 % rst $end
$var reg 1 & sensor_salida $end
$var reg 1 ' sensor_vehiculo $end
$scope module dut $end
$var wire 1 " bit_serial $end
$var wire 1 # clk $end
$var wire 1 $ dato_listo $end
$var wire 1 % rst $end
$var wire 1 & sensor_salida $end
$var wire 1 ' sensor_vehiculo $end
$var wire 1 ( timer_enable $end
$var wire 1 ) timer_done $end
$var wire 1 * shift_enable $end
$var wire 1 ! servo_pwm $end
$var wire 1 + servo_cerrar $end
$var wire 1 , servo_abrir $end
$var wire 8 - password_data [7:0] $end
$var wire 1 . id_correcto $end
$var wire 1 / comparar_enable $end
$scope module comp0 $end
$var wire 1 . id_correcto $end
$var wire 8 0 data [7:0] $end
$upscope $end
$scope module fsm0 $end
$var wire 1 # clk $end
$var wire 1 $ dato_listo $end
$var wire 1 . id_correcto $end
$var wire 1 % rst $end
$var wire 1 & sensor_salida $end
$var wire 1 ' sensor_vehiculo $end
$var wire 1 ) timer_done $end
$var reg 1 / comparar_enable $end
$var reg 3 1 estado_actual [2:0] $end
$var reg 1 , servo_abrir $end
$var reg 1 + servo_cerrar $end
$var reg 1 * shift_enable $end
$var reg 3 2 siguiente_estado [2:0] $end
$var reg 1 ( timer_enable $end
$upscope $end
$scope module servo0 $end
$var wire 1 , abrir $end
$var wire 1 + cerrar $end
$var wire 1 # clk $end
$var wire 1 % rst $end
$var reg 32 3 counter [31:0] $end
$var reg 32 4 pulse_width [31:0] $end
$var reg 1 ! servo_pwm $end
$upscope $end
$scope module shift0 $end
$var wire 1 # clk $end
$var wire 1 * enable $end
$var wire 1 % rst $end
$var wire 1 " serial_in $end
$var reg 8 5 data [7:0] $end
$upscope $end
$scope module timer0 $end
$var wire 1 # clk $end
$var wire 1 ( enable $end
$var wire 1 % rst $end
$var reg 32 6 counter [31:0] $end
$var reg 1 ) done $end
$upscope $end
$upscope $end
$scope task send_password $end
$var reg 8 7 password [7:0] $end
$var integer 32 8 i [31:0] $end
$upscope $end
$upscope $end
$enddefinitions $end
#0
$dumpvars
bx 8
bx 7
bx 6
bx 5
bx 4
bx 3
b0 2
bx 1
bx 0
x/
x.
bx -
x,
x+
x*
x)
x(
0'
0&
1%
0$
0#
0"
x!
$end
#10000
0(
0+
0,
0/
0*
1!
0.
b0 -
b0 0
b0 5
0)
b0 6
b0 1
b1100001101010000 4
b0 3
1#
#20000
0#
#30000
1#
#40000
0#
#50000
1#
#60000
0#
#70000
1#
#80000
0#
#90000
1#
#100000
0#
0%
#110000
b1 3
1#
#120000
0#
#130000
b10 3
1#
#140000
0#
#150000
b11 3
1#
#160000
0#
#170000
b100 3
1#
#180000
0#
#190000
b101 3
1#
#200000
b1 2
0#
1'
#210000
1*
b1 1
b110 3
1#
#220000
0#
#230000
b111 3
1#
#240000
0#
#250000
b1000 3
1#
#260000
0#
#270000
b1001 3
1#
#280000
0#
#290000
b1010 3
1#
#300000
0#
#310000
b1011 3
1#
#320000
0#
#330000
b1100 3
1#
#340000
0#
#350000
b1101 3
1#
#360000
0#
#370000
b1110 3
1#
#380000
0#
#390000
b1111 3
1#
#400000
0#
0'
#410000
b10000 3
1#
#420000
0#
#430000
b10001 3
1#
#440000
0#
#450000
b10010 3
1#
#460000
0#
#470000
b10011 3
1#
#480000
0#
#490000
b10100 3
1#
#500000
0#
1"
b111 8
b10110011 7
#510000
b10101 3
b1 -
b1 0
b1 5
1#
#520000
0#
0"
b110 8
#530000
b10 -
b10 0
b10 5
b10110 3
1#
#540000
0#
1"
b101 8
#550000
b10111 3
b101 -
b101 0
b101 5
1#
#560000
0#
b100 8
#570000
b1011 -
b1011 0
b1011 5
b11000 3
1#
#580000
0#
0"
b11 8
#590000
b11001 3
b10110 -
b10110 0
b10110 5
1#
#600000
0#
b10 8
#610000
b101100 -
b101100 0
b101100 5
b11010 3
1#
#620000
0#
1"
b1 8
#630000
b11011 3
b1011001 -
b1011001 0
b1011001 5
1#
#640000
b10 2
0#
1$
b0 8
#650000
1/
0*
b11 2
1.
b10110011 -
b10110011 0
b10110011 5
b10 1
b11100 3
1#
#660000
0#
#670000
1(
1,
0/
b11101 3
b11 1
1#
#680000
0#
0$
#690000
b1 6
b11000011010100000 4
b11110 3
1#
#700000
0#
#710000
b11111 3
b10 6
1#
#720000
0#
#730000
b11 6
b100000 3
1#
#740000
0#
#750000
b100001 3
b100 6
1#
#760000
0#
#770000
b101 6
b100010 3
1#
#780000
0#
#790000
b100011 3
b110 6
1#
#800000
0#
#810000
b111 6
b100100 3
1#
#820000
0#
#830000
b100101 3
b1000 6
1#
#840000
0#
#850000
b1001 6
b100110 3
1#
#860000
0#
#870000
b100111 3
b1010 6
1#
#880000
0#
#890000
b1011 6
b101000 3
1#
#900000
0#
#910000
b101001 3
b1100 6
1#
#920000
0#
#930000
b1101 6
b101010 3
1#
#940000
0#
#950000
b101011 3
b1110 6
1#
#960000
0#
#970000
b1111 6
b101100 3
1#
#980000
0#
#990000
b101101 3
b10000 6
1#
#1000000
0#
#1010000
b10001 6
b101110 3
1#
#1020000
0#
#1030000
b101111 3
b10010 6
1#
#1040000
0#
#1050000
b10011 6
b110000 3
1#
#1060000
0#
#1070000
b100 2
b110001 3
1)
b0 6
1#
#1080000
0#
#1090000
0(
0,
0)
b1 6
b100 1
b110010 3
1#
#1100000
0#
#1110000
b110011 3
b0 6
1#
#1120000
0#
#1130000
b110100 3
1#
#1140000
0#
#1150000
b110101 3
1#
#1160000
0#
#1170000
b110110 3
1#
#1180000
0#
#1190000
b110111 3
1#
#1200000
0#
#1210000
b111000 3
1#
#1220000
0#
#1230000
b111001 3
1#
#1240000
0#
#1250000
b111010 3
1#
#1260000
0#
#1270000
b111011 3
1#
#1280000
0#
#1290000
b111100 3
1#
#1300000
0#
#1310000
b111101 3
1#
#1320000
0#
#1330000
b111110 3
1#
#1340000
0#
#1350000
b111111 3
1#
#1360000
0#
#1370000
b1000000 3
1#
#1380000
0#
#1390000
b1000001 3
1#
#1400000
0#
#1410000
b1000010 3
1#
#1420000
0#
#1430000
b1000011 3
1#
#1440000
0#
#1450000
b1000100 3
1#
#1460000
0#
#1470000
b1000101 3
1#
#1480000
0#
#1490000
b1000110 3
1#
#1500000
0#
#1510000
b1000111 3
1#
#1520000
0#
#1530000
b1001000 3
1#
#1540000
0#
#1550000
b1001001 3
1#
#1560000
0#
#1570000
b1001010 3
1#
#1580000
0#
#1590000
b1001011 3
1#
#1600000
0#
#1610000
b1001100 3
1#
#1620000
0#
#1630000
b1001101 3
1#
#1640000
0#
#1650000
b1001110 3
1#
#1660000
0#
#1670000
b1001111 3
1#
#1680000
b101 2
0#
1&
#1690000
1(
1+
b101 1
b1010000 3
1#
#1700000
0#
#1710000
b1010001 3
b1100001101010000 4
b1 6
1#
#1720000
0#
#1730000
b10 6
b1010010 3
1#
#1740000
0#
#1750000
b1010011 3
b11 6
1#
#1760000
0#
#1770000
b100 6
b1010100 3
1#
#1780000
0#
#1790000
b1010101 3
b101 6
1#
#1800000
0#
#1810000
b110 6
b1010110 3
1#
#1820000
0#
#1830000
b1010111 3
b111 6
1#
#1840000
0#
#1850000
b1000 6
b1011000 3
1#
#1860000
0#
#1870000
b1011001 3
b1001 6
1#
#1880000
0#
0&
#1890000
b1010 6
b1011010 3
1#
#1900000
0#
#1910000
b1011011 3
b1011 6
1#
#1920000
0#
#1930000
b1100 6
b1011100 3
1#
#1940000
0#
#1950000
b1011101 3
b1101 6
1#
#1960000
0#
#1970000
b1110 6
b1011110 3
1#
#1980000
0#
#1990000
b1011111 3
b1111 6
1#
#2000000
0#
#2010000
b10000 6
b1100000 3
1#
#2020000
0#
#2030000
b1100001 3
b10001 6
1#
#2040000
0#
#2050000
b10010 6
b1100010 3
1#
#2060000
0#
#2070000
b1100011 3
b10011 6
1#
#2080000
0#
#2090000
b0 2
1)
b0 6
b1100100 3
1#
#2100000
0#
#2110000
0(
0+
b1100101 3
b0 1
0)
b1 6
1#
#2120000
0#
#2130000
b0 6
b1100110 3
1#
#2140000
0#
#2150000
b1100111 3
1#
#2160000
0#
#2170000
b1101000 3
1#
#2180000
0#
#2190000
b1101001 3
1#
#2200000
0#
#2210000
b1101010 3
1#
#2220000
0#
#2230000
b1101011 3
1#
#2240000
0#
#2250000
b1101100 3
1#
#2260000
0#
#2270000
b1101101 3
1#
#2280000
0#
#2290000
b1101110 3
1#
#2300000
0#
#2310000
b1101111 3
1#
#2320000
0#
#2330000
b1110000 3
1#
#2340000
0#
#2350000
b1110001 3
1#
#2360000
0#
#2370000
b1110010 3
1#
#2380000
0#
#2390000
b1110011 3
1#
#2400000
0#
#2410000
b1110100 3
1#
#2420000
0#
#2430000
b1110101 3
1#
#2440000
0#
#2450000
b1110110 3
1#
#2460000
0#
#2470000
b1110111 3
1#
#2480000
0#
#2490000
b1111000 3
1#
#2500000
0#
#2510000
b1111001 3
1#
#2520000
0#
#2530000
b1111010 3
1#
#2540000
0#
#2550000
b1111011 3
1#
#2560000
0#
#2570000
b1111100 3
1#
#2580000
0#
#2590000
b1111101 3
1#
#2600000
0#
#2610000
b1111110 3
1#
#2620000
0#
#2630000
b1111111 3
1#
#2640000
0#
#2650000
b10000000 3
1#
#2660000
0#
#2670000
b10000001 3
1#
#2680000
0#
#2690000
b10000010 3
1#
#2700000
0#
#2710000
b10000011 3
1#
#2720000
0#
#2730000
b10000100 3
1#
#2740000
0#
#2750000
b10000101 3
1#
#2760000
0#
#2770000
b10000110 3
1#
#2780000
0#
#2790000
b10000111 3
1#
#2800000
0#
#2810000
b10001000 3
1#
#2820000
0#
#2830000
b10001001 3
1#
#2840000
0#
#2850000
b10001010 3
1#
#2860000
0#
#2870000
b10001011 3
1#
#2880000
0#
#2890000
b10001100 3
1#
#2900000
0#
#2910000
b10001101 3
1#
#2920000
0#
#2930000
b10001110 3
1#
#2940000
0#
#2950000
b10001111 3
1#
#2960000
0#
#2970000
b10010000 3
1#
#2980000
0#
#2990000
b10010001 3
1#
#3000000
0#
#3010000
b10010010 3
1#
#3020000
0#
#3030000
b10010011 3
1#
#3040000
0#
#3050000
b10010100 3
1#
#3060000
0#
#3070000
b10010101 3
1#
#3080000
0#
#3090000
b10010110 3
1#
#3100000
0#
#3110000
b10010111 3
1#
#3120000
0#
#3130000
b10011000 3
1#
#3140000
0#
#3150000
b10011001 3
1#
#3160000
0#
#3170000
b10011010 3
1#
#3180000
0#
#3190000
b10011011 3
1#
#3200000
0#
#3210000
b10011100 3
1#
#3220000
0#
#3230000
b10011101 3
1#
#3240000
0#
#3250000
b10011110 3
1#
#3260000
0#
#3270000
b10011111 3
1#
#3280000
0#
#3290000
b10100000 3
1#
#3300000
0#
#3310000
b10100001 3
1#
#3320000
0#
#3330000
b10100010 3
1#
#3340000
0#
#3350000
b10100011 3
1#
#3360000
0#
#3370000
b10100100 3
1#
#3380000
b1 2
0#
1'
#3390000
1*
b10100101 3
b1 1
1#
#3400000
0#
#3410000
0.
b1100111 -
b1100111 0
b1100111 5
b10100110 3
1#
#3420000
0#
0'
#3430000
b10100111 3
b11001111 -
b11001111 0
b11001111 5
1#
#3440000
0#
#3450000
b10011111 -
b10011111 0
b10011111 5
b10101000 3
1#
#3460000
0#
#3470000
b10101001 3
b111111 -
b111111 0
b111111 5
1#
#3480000
0#
#3490000
b1111111 -
b1111111 0
b1111111 5
b10101010 3
1#
#3500000
0#
#3510000
b10101011 3
b11111111 -
b11111111 0
b11111111 5
1#
#3520000
0#
b111 8
b11111111 7
#3530000
b10101100 3
1#
#3540000
0#
b110 8
#3550000
b10101101 3
1#
#3560000
0#
b101 8
#3570000
b10101110 3
1#
#3580000
0#
b100 8
#3590000
b10101111 3
1#
#3600000
0#
b11 8
#3610000
b10110000 3
1#
#3620000
0#
b10 8
#3630000
b10110001 3
1#
#3640000
0#
b1 8
#3650000
b10110010 3
1#
#3660000
b10 2
0#
1$
b0 8
#3670000
1/
0*
b0 2
b10110011 3
b10 1
1#
#3680000
0#
#3690000
0/
b0 1
b10110100 3
1#
#3700000
0#
0$
#3710000
b10110101 3
1#
#3720000
0#
#3730000
b10110110 3
1#
#3740000
0#
#3750000
b10110111 3
1#
#3760000
0#
#3770000
b10111000 3
1#
#3780000
0#
#3790000
b10111001 3
1#
#3800000
0#
#3810000
b10111010 3
1#
#3820000
0#
#3830000
b10111011 3
1#
#3840000
0#
#3850000
b10111100 3
1#
#3860000
0#
#3870000
b10111101 3
1#
#3880000
0#
#3890000
b10111110 3
1#
#3900000
0#
#3910000
b10111111 3
1#
#3920000
0#
#3930000
b11000000 3
1#
#3940000
0#
#3950000
b11000001 3
1#
#3960000
0#
#3970000
b11000010 3
1#
#3980000
0#
#3990000
b11000011 3
1#
#4000000
0#
#4010000
b11000100 3
1#
#4020000
0#
#4030000
b11000101 3
1#
#4040000
0#
#4050000
b11000110 3
1#
#4060000
0#
#4070000
b11000111 3
1#
#4080000
0#
#4090000
b11001000 3
1#
#4100000
0#
#4110000
b11001001 3
1#
#4120000
0#
#4130000
b11001010 3
1#
#4140000
0#
#4150000
b11001011 3
1#
#4160000
0#
#4170000
b11001100 3
1#
#4180000
0#
#4190000
b11001101 3
1#
#4200000
b1 2
0#
1'
#4210000
1*
b1 1
b11001110 3
1#
#4220000
0#
#4230000
b11001111 3
1#
#4240000
0#
0'
#4250000
b11010000 3
1#
#4260000
0#
#4270000
b11010001 3
1#
#4280000
0#
#4290000
b11010010 3
1#
#4300000
0#
#4310000
b11010011 3
1#
#4320000
0#
#4330000
b11010100 3
1#
#4340000
0#
#4350000
b11010101 3
1#
#4360000
0#
#4370000
b11010110 3
1#
#4380000
0#
#4390000
b11010111 3
1#
#4400000
0#
#4410000
b11011000 3
1#
#4420000
0#
#4430000
b11011001 3
1#
#4440000
0#
#4450000
b11011010 3
1#
#4460000
0#
#4470000
b11011011 3
1#
#4480000
0#
#4490000
b11011100 3
1#
#4500000
0#
#4510000
b11011101 3
1#
#4520000
0#
#4530000
b11011110 3
1#
#4540000
0#
#4550000
b11011111 3
1#
#4560000
0#
#4570000
b11100000 3
1#
#4580000
0#
#4590000
b11100001 3
1#
#4600000
0#
#4610000
b11100010 3
1#
#4620000
0#
#4630000
b11100011 3
1#
#4640000
0#
#4650000
b11100100 3
1#
#4660000
0#
#4670000
b11100101 3
1#
#4680000
0#
#4690000
b11100110 3
1#
#4700000
0#
#4710000
b11100111 3
1#
#4720000
0#
#4730000
b11101000 3
1#
#4740000
0#
#4750000
b11101001 3
1#
#4760000
0#
#4770000
b11101010 3
1#
#4780000
0#
#4790000
b11101011 3
1#
#4800000
0#
#4810000
b11101100 3
1#
#4820000
0#
#4830000
b11101101 3
1#
#4840000
0#
#4850000
b11101110 3
1#
#4860000
0#
#4870000
b11101111 3
1#
#4880000
0#
#4890000
b11110000 3
1#
#4900000
0#
#4910000
b11110001 3
1#
#4920000
0#
#4930000
b11110010 3
1#
#4940000
0#
#4950000
b11110011 3
1#
#4960000
0#
#4970000
b11110100 3
1#
#4980000
0#
#4990000
b11110101 3
1#
#5000000
0#
#5010000
b11110110 3
1#
#5020000
0#
#5030000
b11110111 3
1#
#5040000
0#
#5050000
b11111000 3
1#
#5060000
0#
#5070000
b11111001 3
1#
#5080000
0#
#5090000
b11111010 3
1#
#5100000
0#
#5110000
b11111011 3
1#
#5120000
0#
#5130000
b11111100 3
1#
#5140000
0#
#5150000
b11111101 3
1#
#5160000
0#
#5170000
b11111110 3
1#
#5180000
0#
#5190000
b11111111 3
1#
#5200000
0#
#5210000
b100000000 3
1#
#5220000
0#
#5230000
b100000001 3
1#
#5240000
0#
1%
#5250000
0*
b0 2
b0 -
b0 0
b0 5
b0 1
b0 3
1#
#5260000
0#
#5270000
1#
#5280000
0#
0%
#5290000
b1 3
1#
#5300000
0#
#5310000
b10 3
1#
#5320000
0#
#5330000
b11 3
1#
#5340000
0#
#5350000
b100 3
1#
#5360000
0#
#5370000
b101 3
1#
#5380000
b1 2
0#
1'
#5390000
1*
b110 3
b1 1
1#
#5400000
0#
#5410000
b1 -
b1 0
b1 5
b111 3
1#
#5420000
0#
0'
#5430000
b1000 3
b11 -
b11 0
b11 5
1#
#5440000
0#
#5450000
b111 -
b111 0
b111 5
b1001 3
1#
#5460000
0#
#5470000
b1010 3
b1111 -
b1111 0
b1111 5
1#
#5480000
0#
#5490000
b11111 -
b11111 0
b11111 5
b1011 3
1#
#5500000
0#
#5510000
b1100 3
b111111 -
b111111 0
b111111 5
1#
#5520000
0#
b111 8
b10110011 7
#5530000
b1111111 -
b1111111 0
b1111111 5
b1101 3
1#
#5540000
0#
0"
b110 8
#5550000
b1110 3
b11111110 -
b11111110 0
b11111110 5
1#
#5560000
0#
1"
b101 8
#5570000
b11111101 -
b11111101 0
b11111101 5
b1111 3
1#
#5580000
0#
b100 8
#5590000
b10000 3
b11111011 -
b11111011 0
b11111011 5
1#
#5600000
0#
0"
b11 8
#5610000
b11110110 -
b11110110 0
b11110110 5
b10001 3
1#
#5620000
0#
b10 8
#5630000
b10010 3
b11101100 -
b11101100 0
b11101100 5
1#
#5640000
0#
1"
b1 8
#5650000
b11011001 -
b11011001 0
b11011001 5
b10011 3
1#
#5660000
b10 2
0#
1$
b0 8
#5670000
1/
0*
b11 2
b10100 3
b10 1
1.
b10110011 -
b10110011 0
b10110011 5
1#
#5680000
0#
#5690000
1(
1,
0/
b11 1
b10101 3
1#
#5700000
0#
0$
#5710000
b10110 3
b11000011010100000 4
b1 6
1#
#5720000
0#
#5730000
b10 6
b10111 3
1#
#5740000
0#
#5750000
b11000 3
b11 6
1#
#5760000
0#
#5770000
b100 6
b11001 3
1#
#5780000
0#
#5790000
b11010 3
b101 6
1#
#5800000
0#
#5810000
b110 6
b11011 3
1#
#5820000
0#
#5830000
b11100 3
b111 6
1#
#5840000
0#
#5850000
b1000 6
b11101 3
1#
#5860000
0#
#5870000
b11110 3
b1001 6
1#
#5880000
0#
#5890000
b1010 6
b11111 3
1#
#5900000
0#
#5910000
b100000 3
b1011 6
1#
#5920000
0#
#5930000
b1100 6
b100001 3
1#
#5940000
0#
#5950000
b100010 3
b1101 6
1#
#5960000
0#
#5970000
b1110 6
b100011 3
1#
#5980000
0#
#5990000
b100100 3
b1111 6
1#
#6000000
0#
#6010000
b10000 6
b100101 3
1#
#6020000
0#
#6030000
b100110 3
b10001 6
1#
#6040000
0#
#6050000
b10010 6
b100111 3
1#
#6060000
0#
#6070000
b101000 3
b10011 6
1#
#6080000
0#
#6090000
b100 2
1)
b0 6
b101001 3
1#
#6100000
0#
#6110000
0(
0,
b101010 3
b100 1
0)
b1 6
1#
#6120000
0#
#6130000
b0 6
b101011 3
1#
#6140000
0#
#6150000
b101100 3
1#
#6160000
0#
#6170000
b101101 3
1#
#6180000
0#
#6190000
b101110 3
1#
#6200000
0#
#6210000
b101111 3
1#
#6220000
0#
#6230000
b110000 3
1#
#6240000
0#
#6250000
b110001 3
1#
#6260000
0#
#6270000
b110010 3
1#
#6280000
0#
#6290000
b110011 3
1#
#6300000
0#
#6310000
b110100 3
1#
#6320000
0#
#6330000
b110101 3
1#
#6340000
0#
#6350000
b110110 3
1#
#6360000
0#
#6370000
b110111 3
1#
#6380000
0#
#6390000
b111000 3
1#
#6400000
0#
#6410000
b111001 3
1#
#6420000
0#
#6430000
b111010 3
1#
#6440000
0#
#6450000
b111011 3
1#
#6460000
0#
#6470000
b111100 3
1#
#6480000
0#
